{"assets":{"BA3C3DFD157DCE3E5A59CBAA4BDD9261":{"type":"texture","index":0,"assetRequest":{"type":"slide","state":"contents","slide":"none"},"url":{"native":"assets\/FD44A9FD-2CC7-4583-95F9-C05696F5A7B8.pdf"},"width":1920,"height":1080},"643871FBAD4FBF3D2E22D12FE9FE5DF9":{"type":"texture","index":1,"assetRequest":{"type":"slide","state":"contents","slide":"none"},"url":{"native":"assets\/FD44A9FD-2CC7-4583-95F9-C05696F5A7B8.pdf"},"width":1920,"height":1080}},"events":[{"effects":[{"beginTime":0,"baseLayer":{"animations":[],"initialState":{"affineTransform":[1,0,0,1,0,0],"masksToBounds":false,"rotation":0,"scale":1,"position":{"pointX":960,"pointY":540},"width":1920,"sublayerTransform":[1,0,0,0,0,1,0,0,0,0,1,0,0,0,0,1],"contentsRect":{"y":0,"x":0,"width":1,"height":1},"opacity":1,"edgeAntialiasingMask":251658240,"height":1080,"hidden":false,"anchorPoint":{"pointX":0.5,"pointY":0.5}},"objectID":"0","layers":[{"animations":[],"initialState":{"affineTransform":[1,0,0,1,0,0],"masksToBounds":false,"rotation":0,"scale":1,"position":{"pointX":960,"pointY":540},"width":1920,"sublayerTransform":[1,0,0,0,0,1,0,0,0,0,1,-0.00035007912466775983,0,0,0,1],"contentsRect":{"y":0,"x":0,"width":1,"height":1},"opacity":1,"edgeAntialiasingMask":251658240,"height":1080,"hidden":false,"anchorPoint":{"pointX":0.5,"pointY":0.5}},"layers":[{"animations":[],"layers":[],"texturedRectangle":{"isBackgroundTexture":false,"singleTextureOpacity":1,"textureType":0,"textBaseline":0,"textXHeight":0,"isVerticalText":false},"initialState":{"affineTransform":[1,0,0,1,0,0],"masksToBounds":false,"rotation":0,"scale":1,"position":{"pointX":960,"pointY":540},"width":1920,"sublayerTransform":[1,0,0,0,0,1,0,0,0,0,1,0,0,0,0,1],"contentsRect":{"y":0,"x":0,"width":1,"height":1},"opacity":1,"edgeAntialiasingMask":0,"height":1080,"hidden":false,"anchorPoint":{"pointX":0.5,"pointY":0.5}},"texture":"643871FBAD4FBF3D2E22D12FE9FE5DF9"},{"animations":[{"additive":false,"timeOffset":0,"beginTime":0,"from":{"scalar":false},"repeatCount":0,"fillMode":"both","duration":0.01,"autoreverses":false,"property":"hidden","to":{"scalar":true},"removedOnCompletion":false}],"layers":[],"texturedRectangle":{"isBackgroundTexture":false,"singleTextureOpacity":1,"textureType":0,"textBaseline":0,"textXHeight":0,"isVerticalText":false},"initialState":{"affineTransform":[1,0,0,1,0,0],"masksToBounds":false,"rotation":0,"scale":1,"position":{"pointX":960,"pointY":540},"width":1920,"sublayerTransform":[1,0,0,0,0,1,0,0,0,0,1,0,0,0,0,1],"contentsRect":{"y":0,"x":0,"width":1,"height":1},"opacity":1,"edgeAntialiasingMask":0,"height":1080,"hidden":false,"anchorPoint":{"pointX":0.5,"pointY":0.5}},"texture":"BA3C3DFD157DCE3E5A59CBAA4BDD9261"}]}]},"effects":[],"duration":0.01,"type":"transition","attributes":{"direction":0},"name":"none","objectID":"0"}],"automaticPlay":false,"hyperlinks":[],"accessibility":[{"text":"データベース一覧","targetRectangle":{"y":830.27423095703125,"x":751.88185092806816,"width":256,"height":44.125}},{"text":"B. Business Source Premier","targetRectangle":{"y":830.27423095703125,"x":1150.8872024714947,"width":415.0625,"height":44.125}},{"text":"入手方法は3通り","targetRectangle":{"y":214.71343994140625,"x":144.59999847412109,"width":347.43281250000007,"height":63.903124999999989}},{"text":"紙のテキストを生協とかAmazonで購入","targetRectangle":{"y":276.32312591783705,"x":192.59999847412109,"width":807.97500000000025,"height":86.703124713897694}},{"text":"Kindle版","targetRectangle":{"y":360.73281160816549,"x":192.59999847412109,"width":179.81718750000005,"height":86.703124713897694}},{"text":"図書館の論文データベースから，オリジナル版を入手","targetRectangle":{"y":445.14249729849394,"x":192.59999847412109,"width":1094.4000000000003,"height":86.703124713897751}},{"text":"神戸大学図書館のホームページから以下の順番に入って行って，各章のタイトルを検索すると，pdf版が入手可能","targetRectangle":{"y":529.55218298882244,"x":240.59999847412109,"width":1550.4000000000001,"height":148.31281069032855}},{"text":"若干面倒臭いけど無料","targetRectangle":{"y":675.57155465558174,"x":240.59999847412109,"width":456.00000000000011,"height":86.703124713897751}},{"text":"図 6","targetRectangle":{"y":17.255117416381836,"x":1639.83935546875,"width":263.11077880859375,"height":76.828346252441406}},{"text":"図書館トップ","targetRectangle":{"y":830.27423095703125,"x":385.46873447299004,"width":192,"height":44.125}},{"text":"￼","targetRectangle":{"y":1026.4959712028503,"x":954.25799553832621,"width":10.5,"height":29}}],"baseLayer":{"animations":[],"initialState":{"affineTransform":[1,0,0,1,0,0],"masksToBounds":false,"rotation":0,"scale":1,"position":{"pointX":960,"pointY":540},"width":1920,"sublayerTransform":[1,0,0,0,0,1,0,0,0,0,1,0,0,0,0,1],"contentsRect":{"y":0,"x":0,"width":1,"height":1},"opacity":1,"edgeAntialiasingMask":251658240,"height":1080,"hidden":false,"anchorPoint":{"pointX":0.5,"pointY":0.5}},"objectID":"0","layers":[{"animations":[],"initialState":{"affineTransform":[1,0,0,1,0,0],"masksToBounds":false,"rotation":0,"scale":1,"position":{"pointX":960,"pointY":540},"width":1920,"sublayerTransform":[1,0,0,0,0,1,0,0,0,0,1,-0.00035007912466775983,0,0,0,1],"contentsRect":{"y":0,"x":0,"width":1,"height":1},"opacity":1,"edgeAntialiasingMask":251658240,"height":1080,"hidden":false,"anchorPoint":{"pointX":0.5,"pointY":0.5}},"layers":[{"animations":[],"layers":[],"texturedRectangle":{"isBackgroundTexture":false,"singleTextureOpacity":1,"textureType":0,"textBaseline":0,"textXHeight":0,"isVerticalText":false},"initialState":{"affineTransform":[1,0,0,1,0,0],"masksToBounds":false,"rotation":0,"scale":1,"position":{"pointX":960,"pointY":540},"width":1920,"sublayerTransform":[1,0,0,0,0,1,0,0,0,0,1,0,0,0,0,1],"contentsRect":{"y":0,"x":0,"width":1,"height":1},"opacity":1,"edgeAntialiasingMask":0,"height":1080,"hidden":false,"anchorPoint":{"pointX":0.5,"pointY":0.5}},"texture":"BA3C3DFD157DCE3E5A59CBAA4BDD9261"}]}]}}]}